yamlschema/__init__.py
yamlschema/_version.py
yamlschema/lib.py
yamlschema/test/__init__.py
yamlschema/test/test_lib.py
yamlschema-0.2.1.data/scripts/yamlschema
yamlschema-0.2.1.dist-info/DESCRIPTION.rst
yamlschema-0.2.1.dist-info/METADATA
yamlschema-0.2.1.dist-info/RECORD
yamlschema-0.2.1.dist-info/WHEEL
yamlschema-0.2.1.dist-info/metadata.json
yamlschema-0.2.1.dist-info/top_level.txt
