Metadata-Version: 2.0
Name: yamlschema
Version: 0.2.1
Summary: A schema validator for YAML files
Home-page: https://github.com/Brightmd/yamlschema
Author: Ashley Fisher
Author-email: fish.ash@gmail.com
License: UNKNOWN
Keywords: yaml,schema
Platform: UNKNOWN
Requires-Dist: click (<8.0,>=5.0)
Requires-Dist: jsonschema (==2.6.0)
